{"users":[{"nick":"r","pass":"4b43b0aee35624cd95b910189b3dc231","games":{"6":{"5":{"games":4,"victories":4}},"7":{"6":{"games":1,"victories":0}}}},{"nick":"t","pass":"e358efa489f58062f10dd7316b65649e","games":{"6":{"5":{"games":4,"victories":0}},"7":{"6":{"games":1,"victories":1}}}},{"nick":"Diogo","pass":"8277e0910d750195b448797616e091ad","games":{"6":{"5":{"games":1,"victories":1}},"8":{"7":{"games":1,"victories":0}}}},{"nick":"fred","pass":"8fa14cdd754f91cc6554c9e71929cce7","games":{"6":{"5":{"games":1,"victories":0}},"8":{"7":{"games":1,"victories":1}}}},{"nick":"y","pass":"415290769594460e2e485922904f345d","games":{}},{"nick":"q","pass":"7694f4a66316e53c8cdd9d9954bd611d","games":{}}]}